<pc:PcGts xmlns:pc="http://schema.primaresearch.org/PAGE/gts/pagecontent/2019-07-15" xmlns:xsi="http://www.w3.org/2001/XMLSchema-instance" xsi:schemaLocation="http://schema.primaresearch.org/PAGE/gts/pagecontent/2019-07-15 http://schema.primaresearch.org/PAGE/gts/pagecontent/2019-07-15/pagecontent.xsd">
    <pc:Metadata>
        <pc:Creator>OCR-D/core 2.4.4</pc:Creator>
        <pc:Created>2020-06-15T07:22:48</pc:Created>
        <pc:LastChange>2020-06-15T07:22:48</pc:LastChange>
        <pc:MetadataItem type="processingStep" name="preprocessing/optimization/binarization" value="ocrd-olena-binarize">
            <pc:Labels>
                <pc:Label value="sauvola" type="impl"/>
                <pc:Label value="0.34" type="k"/>
                <pc:Label value="101" type="win-size"/>
            </pc:Labels>
        </pc:MetadataItem>
        <pc:MetadataItem type="processingStep" name="preprocessing/optimization/cropping" value="ocrd-anybaseocr-crop">
            <pc:Labels>
                <pc:Label value="True" type="force"/>
                <pc:Label value="0.04" type="colSeparator"/>
                <pc:Label value="0.3" type="maxRularArea"/>
                <pc:Label value="0.05" type="minArea"/>
                <pc:Label value="0.01" type="minRularArea"/>
                <pc:Label value="0.75" type="positionBelow"/>
                <pc:Label value="0.4" type="positionLeft"/>
                <pc:Label value="0.6" type="positionRight"/>
                <pc:Label value="10.0" type="rularRatioMax"/>
                <pc:Label value="3.0" type="rularRatioMin"/>
                <pc:Label value="0.95" type="rularWidth"/>
                <pc:Label value="page" type="operation_level"/>
            </pc:Labels>
        </pc:MetadataItem>
        <pc:MetadataItem type="processingStep" name="layout/segmentation/region" value="ocrd-tesserocr-segment-region">
            <pc:Labels externalModel="ocrd-tool" externalId="parameters">
                <pc:Label value="-1" type="dpi"/>
                <pc:Label value="True" type="overwrite_regions"/>
                <pc:Label value="0" type="padding"/>
                <pc:Label value="False" type="crop_polygons"/>
                <pc:Label value="True" type="find_tables"/>
                <pc:Label value="False" type="sparse_text"/>
            </pc:Labels>
        </pc:MetadataItem>
    </pc:Metadata>
    <pc:Page imageFilename="OCR-D-IMG/Matthaei_1652-059.png" imageWidth="1167" imageHeight="1456" type="content">
        <pc:AlternativeImage filename="OCR-D-IMG-BIN/OCR-D-BIN_Matthaei_1652-059-BIN_sauvola.png" comments="binarized"/>
        <pc:AlternativeImage filename="OCR-D-IMG-CROP/OCR-D-IMG-CROP_Matthaei_1652-059.png" comments="binarized,cropped"/>
        <pc:Border>
            <pc:Coords points="300,112 1047,112 1047,1303 300,1303"/>
        </pc:Border>
        <pc:ReadingOrder>
            <pc:OrderedGroup id="reading-order">
                <pc:RegionRefIndexed index="0" regionRef="region_id_0"/><pc:RegionRefIndexed index="1" regionRef="region_id_1"/><pc:RegionRefIndexed index="2" regionRef="region_id_2"/><pc:RegionRefIndexed index="3" regionRef="region_id_3"/><pc:RegionRefIndexed index="4" regionRef="region_id_4"/><pc:RegionRefIndexed index="5" regionRef="region_id_5"/><pc:RegionRefIndexed index="6" regionRef="region_id_6"/><pc:RegionRefIndexed index="7" regionRef="region_id_7"/><pc:RegionRefIndexed index="8" regionRef="region_id_8"/><pc:RegionRefIndexed index="9" regionRef="region_id_9"/></pc:OrderedGroup>
        </pc:ReadingOrder>
        <pc:TextRegion id="region_id_0" type="footer"><pc:Coords points="1017,1306 941,1302 938,1275 1041,1276 1044,1299 1017,1306"/></pc:TextRegion><pc:TextRegion id="region_id_1" type="paragraph"><pc:Coords points="736,1138 339,1138 316,1106 320,1034 359,1006 418,992 993,990 1022,1006 1026,1083 1009,1116 736,1138"/></pc:TextRegion><pc:TextRegion id="region_id_2" type="paragraph"><pc:Coords points="428,878 331,864 284,838 300,831 284,825 298,818 284,799 314,767 302,760 316,753 302,747 331,718 978,718 1029,728 1068,760 1060,837 987,866 541,858 428,878"/></pc:TextRegion><pc:TextRegion id="region_id_3" type="paragraph"><pc:Coords points="456,974 315,964 326,961 302,958 314,938 304,934 330,910 414,896 999,898 1074,916 1038,952 972,964 456,974"/></pc:TextRegion><pc:TextRegion id="region_id_4" type="paragraph"><pc:Coords points="425,668 318,663 306,638 317,552 370,540 1023,540 1042,552 1036,648 987,660 658,652 425,668"/></pc:TextRegion><pc:TextRegion id="region_id_5" type="paragraph"><pc:Coords points="967,452 388,448 313,430 286,408 302,405 284,401 298,391 282,387 337,358 397,354 1044,360 1048,437 967,452"/></pc:TextRegion><pc:TextRegion id="region_id_6" type="paragraph"><pc:Coords points="657,1284 338,1276 308,1263 318,1258 302,1253 300,1213 312,1184 330,1179 318,1174 351,1136 1031,1125 1057,1163 1054,1223 1008,1244 961,1240 956,1278 657,1284"/></pc:TextRegion><pc:TextRegion id="region_id_7" type="heading"><pc:Coords points="793,273 384,259 384,214 440,209 519,207 538,157 780,151 792,164 802,189 807,207 949,220 954,242 953,265 793,273"/></pc:TextRegion><pc:TextRegion id="region_id_8" type="paragraph"><pc:Coords points="968,758 362,756 306,742 296,716 308,700 378,684 1025,684 1030,746 968,758"/></pc:TextRegion><pc:TextRegion id="region_id_9" type="header"><pc:Coords points="758,145 285,153 290,119 794,115 797,133 793,143 758,145"/></pc:TextRegion></pc:Page>
</pc:PcGts>